d2l/__init__.py
d2l/helpers.py
d2l/unpacker.py
bcit_tools-0.2.5.dist-info/METADATA
bcit_tools-0.2.5.dist-info/WHEEL
bcit_tools-0.2.5.dist-info/top_level.txt
bcit_tools-0.2.5.dist-info/RECORD
