Metadata-Version: 2.1
Name: bcit-tools
Version: 0.2.5
Summary: A package to deal with BCIT tools
Home-page: https://github.com/timoguic/bcit-utils/tree/master/bcit_tools
Author: Tim G
Author-email: timoguic@gmail.com
License: UNKNOWN
Platform: UNKNOWN
Classifier: Programming Language :: Python :: 3
Classifier: License :: OSI Approved :: MIT License
Classifier: Operating System :: OS Independent
Requires-Python: >=3.6
